{
  "source": "OMMAS — pmgsy.dord.gov.in",
  "retrieved": "2026-05-05",
  "note": "Representative PMGSY road records for Pan-India. Cross-referenced with data.gov.in NH length dataset.",
  "district": "Pan-India",
  "state": "Pan-India",
  "total_roads": 12,
  "roads": [
    {
      "road_id": "MH-PUN-PMGSY-012",
      "name": "Hinjewadi to Mulshi Link Road",
      "block": "Mulshi",
      "district": "Pune",
      "state": "Maharashtra",
      "length_km": 14.2,
      "width_m": 5.5,
      "surface": "Bituminous",
      "contractor": "M/s Western Ghats Infra",
      "contractor_id": "WGI-2021-089",
      "sanctioned_cost_lakh": 210.5,
      "expenditure_lakh": 208.3,
      "completion_date": "2022-05-15",
      "maintenance_end": "2027-05-15",
      "quality_score": 8.2,
      "last_inspection": "2025-10-20",
      "status": "Completed"
    },
    {
      "road_id": "UP-LKO-PMGSY-045",
      "name": "Malihabad to Kakori Connector",
      "block": "Malihabad",
      "district": "Lucknow",
      "state": "Uttar Pradesh",
      "length_km": 18.5,
      "width_m": 5.0,
      "surface": "Bituminous",
      "contractor": "M/s Northern Road Builders",
      "contractor_id": "NRB-2020-112",
      "sanctioned_cost_lakh": 275.5,
      "expenditure_lakh": 271.8,
      "completion_date": "2021-11-22",
      "maintenance_end": "2026-11-22",
      "quality_score": 5.2,
      "last_inspection": "2025-11-05",
      "status": "Completed — Quality Concern"
    },
    {
      "road_id": "KA-BLR-PMGSY-098",
      "name": "Nelamangala to Magadi Road",
      "block": "Nelamangala",
      "district": "Bangalore Rural",
      "state": "Karnataka",
      "length_km": 25.2,
      "width_m": 7.0,
      "surface": "Concrete",
      "contractor": "M/s Deccan Roadways Ltd",
      "contractor_id": "DRL-2022-078",
      "sanctioned_cost_lakh": 542.0,
      "expenditure_lakh": 538.5,
      "completion_date": "2023-04-10",
      "maintenance_end": "2028-04-10",
      "quality_score": 8.9,
      "last_inspection": "2025-12-01",
      "status": "Completed"
    },
    {
      "road_id": "WB-HGL-PMGSY-034",
      "name": "Singur to Tarakeshwar Route",
      "block": "Singur",
      "district": "Hooghly",
      "state": "West Bengal",
      "length_km": 11.1,
      "width_m": 4.5,
      "surface": "WBM",
      "contractor": "M/s Eastern Infra Corp",
      "contractor_id": "EIC-2020-112",
      "sanctioned_cost_lakh": 113.2,
      "expenditure_lakh": 111.9,
      "completion_date": "2020-12-05",
      "maintenance_end": "2025-12-05",
      "quality_score": 4.1,
      "last_inspection": "2025-09-18",
      "status": "Deteriorated — Under 5yr Warranty"
    },
    {
      "road_id": "TN-CGL-PMGSY-001",
      "name": "Mamallapuram to Thirukkazhukundram Road",
      "block": "Thiruporur",
      "district": "Chengalpattu",
      "state": "Tamil Nadu",
      "length_km": 12.5,
      "width_m": 5.5,
      "surface": "Bituminous",
      "contractor": "M/s Tamil Nadu Road Builders",
      "contractor_id": "TNRB-2021-045",
      "sanctioned_cost_lakh": 187.5,
      "expenditure_lakh": 182.3,
      "completion_date": "2022-03-15",
      "maintenance_end": "2027-03-15",
      "quality_score": 7.8,
      "last_inspection": "2025-11-20",
      "status": "Completed"
    },
    {
      "road_id": "GJ-AMD-PMGSY-077",
      "name": "Sanand to Viramgam Connector",
      "block": "Sanand",
      "district": "Ahmedabad",
      "state": "Gujarat",
      "length_km": 28.0,
      "width_m": 7.0,
      "surface": "Concrete",
      "contractor": "M/s Gujarat State Highways",
      "contractor_id": "GSH-2023-019",
      "sanctioned_cost_lakh": 496.0,
      "expenditure_lakh": 494.5,
      "completion_date": "2024-02-28",
      "maintenance_end": "2029-02-28",
      "quality_score": 9.3,
      "last_inspection": "2025-12-15",
      "status": "Completed — Excellent"
    },
    {
      "road_id": "BR-PTN-PMGSY-022",
      "name": "Danapur to Maner Link",
      "block": "Danapur",
      "district": "Patna",
      "state": "Bihar",
      "length_km": 16.4,
      "width_m": 5.0,
      "surface": "Bituminous",
      "contractor": "M/s Northern Road Builders",
      "contractor_id": "NRB-2020-112",
      "sanctioned_cost_lakh": 210.0,
      "expenditure_lakh": 208.5,
      "completion_date": "2021-05-10",
      "maintenance_end": "2026-05-10",
      "quality_score": 3.8,
      "last_inspection": "2025-08-14",
      "status": "Severe Potholes — Flagged"
    },
    {
      "road_id": "AS-KMP-PMGSY-011",
      "name": "Sonapur to Jagiroad Bypass",
      "block": "Sonapur",
      "district": "Kamrup",
      "state": "Assam",
      "length_km": 21.0,
      "width_m": 5.5,
      "surface": "Bituminous",
      "contractor": "M/s Brahmaputra Infra",
      "contractor_id": "BPI-2021-088",
      "sanctioned_cost_lakh": 315.0,
      "expenditure_lakh": 310.2,
      "completion_date": "2022-12-01",
      "maintenance_end": "2027-12-01",
      "quality_score": 6.5,
      "last_inspection": "2025-07-22",
      "status": "Completed"
    },
    {
      "road_id": "RJ-JPR-PMGSY-055",
      "name": "Chomu to Renwal Route",
      "block": "Chomu",
      "district": "Jaipur",
      "state": "Rajasthan",
      "length_km": 32.5,
      "width_m": 7.0,
      "surface": "Concrete",
      "contractor": "M/s Desert Constructors",
      "contractor_id": "DC-2022-105",
      "sanctioned_cost_lakh": 650.0,
      "expenditure_lakh": 645.8,
      "completion_date": "2023-11-15",
      "maintenance_end": "2028-11-15",
      "quality_score": 8.7,
      "last_inspection": "2025-10-10",
      "status": "Completed"
    },
    {
      "road_id": "PB-LDH-PMGSY-088",
      "name": "Jagraon to Raikot Road",
      "block": "Jagraon",
      "district": "Ludhiana",
      "state": "Punjab",
      "length_km": 19.8,
      "width_m": 5.5,
      "surface": "Bituminous",
      "contractor": "M/s Northern Road Builders",
      "contractor_id": "NRB-2020-112",
      "sanctioned_cost_lakh": 240.0,
      "expenditure_lakh": 238.1,
      "completion_date": "2021-09-30",
      "maintenance_end": "2026-09-30",
      "quality_score": 5.8,
      "last_inspection": "2025-09-05",
      "status": "Requires Maintenance"
    },
    {
      "road_id": "KL-EKM-PMGSY-033",
      "name": "Aluva to Perumbavoor Link",
      "block": "Aluva",
      "district": "Ernakulam",
      "state": "Kerala",
      "length_km": 14.5,
      "width_m": 5.5,
      "surface": "Bituminous",
      "contractor": "M/s Southern Infrastructure Corp",
      "contractor_id": "SIC-2020-112",
      "sanctioned_cost_lakh": 185.0,
      "expenditure_lakh": 182.5,
      "completion_date": "2022-01-20",
      "maintenance_end": "2027-01-20",
      "quality_score": 7.2,
      "last_inspection": "2025-11-28",
      "status": "Completed"
    },
    {
      "road_id": "MP-IND-PMGSY-099",
      "name": "Mhow to Pithampur Road",
      "block": "Mhow",
      "district": "Indore",
      "state": "Madhya Pradesh",
      "length_km": 12.0,
      "width_m": 7.0,
      "surface": "Concrete",
      "contractor": "M/s Central India Builders",
      "contractor_id": "CIB-2023-042",
      "sanctioned_cost_lakh": 290.0,
      "expenditure_lakh": 288.5,
      "completion_date": "2024-01-10",
      "maintenance_end": "2029-01-10",
      "quality_score": 9.0,
      "last_inspection": "2025-12-05",
      "status": "Completed — Excellent"
    }
  ]
}